bbrpy/__init__.py
bbrpy/cli.py
bbrpy/generator.py
bbrpy/models.py
bbrpy/version.py
bbrpy-3.1.0.dist-info/METADATA
bbrpy-3.1.0.dist-info/WHEEL
bbrpy-3.1.0.dist-info/entry_points.txt
bbrpy-3.1.0.dist-info/licenses/LICENSE
bbrpy-3.1.0.dist-info/RECORD
