Metadata-Version: 2.4
Name: bbrpy
Version: 3.1.0
Summary: Better Battery Report for Windows
Author-email: Pablo Garcia <pablofueros@gmail.com>
License-File: LICENSE
Classifier: License :: OSI Approved :: MIT License
Classifier: Operating System :: Microsoft :: Windows
Classifier: Programming Language :: Python :: 3
Classifier: Programming Language :: Python :: 3.12
Requires-Python: >=3.12
Requires-Dist: pydantic-xml>=2.14.1
Requires-Dist: rich>=13.9.4
Requires-Dist: typer>=0.15.1
Provides-Extra: report
Requires-Dist: pandas>=2.2.3; extra == 'report'
Requires-Dist: plotly>=5.24.1; extra == 'report'
